DSC_NSD_TEST/DSC_NSD_TEST.py
DSC_NSD_TEST/__init__.py
DSC_NSD_TEST-0.0.1.dist-info/LICENSE
DSC_NSD_TEST-0.0.1.dist-info/METADATA
DSC_NSD_TEST-0.0.1.dist-info/WHEEL
DSC_NSD_TEST-0.0.1.dist-info/top_level.txt
DSC_NSD_TEST-0.0.1.dist-info/RECORD
